diskcsvsort/__init__.py
diskcsvsort/__main__.py
diskcsvsort/cli/__init__.py
diskcsvsort/cli/columns.py
diskcsvsort/cli/diskcsvsort_cli.py
diskcsvsort/csvsort.py
diskcsvsort/enums.py
diskcsvsort/errors.py
diskcsvsort/infany.py
diskcsvsort/temp.py
diskcsvsort-0.1.1.dist-info/LICENSE
diskcsvsort-0.1.1.dist-info/WHEEL
diskcsvsort-0.1.1.dist-info/METADATA
diskcsvsort-0.1.1.dist-info/RECORD
