Metadata-Version: 2.1
Name: diskcsvsort
Version: 0.1.1
Summary: Sort huge csv files.
Home-page: https://github.com/VolodymyrBor/diskcsvsort
License: MIT
Author: volodymyrb
Author-email: volodymyr.borysiuk0@gmail.com
Requires-Python: >=3.10,<4.0
Classifier: License :: OSI Approved :: MIT License
Classifier: Programming Language :: Python :: 3
Classifier: Programming Language :: Python :: 3.10
Requires-Dist: typer (>=0.4.0,<0.5.0)
Project-URL: Repository, https://github.com/VolodymyrBor/diskcsvsort
